[
   {  
      "logo":"PanelTop",
      "title": "Frontend",
      "skills_details": [
         "JavaScript",
         "React.js",
         "HTML5 & CSS3",
         "Responsive Design"
      ]
   },
   { 
      "logo":"Server",
      "title": "Backend",
      "skills_details": [
         "PHP (bases)",
         "MySQL (bases)",
         "Node.js (initiation)"
      ]
   },
   {  
      "logo":"User",
      "title": "Soft Skills",
      "skills_details": [
         "Communication",
         "Gestion du temps",
         "Travail en équipe"
      ]
   }
]